CHANGES.rst
MANIFEST.in
README.rst
setup.py
collective/__init__.py
collective.registrationcaptcha.egg-info/PKG-INFO
collective.registrationcaptcha.egg-info/SOURCES.txt
collective.registrationcaptcha.egg-info/dependency_links.txt
collective.registrationcaptcha.egg-info/entry_points.txt
collective.registrationcaptcha.egg-info/namespace_packages.txt
collective.registrationcaptcha.egg-info/not-zip-safe
collective.registrationcaptcha.egg-info/requires.txt
collective.registrationcaptcha.egg-info/top_level.txt
collective/registrationcaptcha/__init__.py
collective/registrationcaptcha/configure.zcml
collective/registrationcaptcha/interfaces.py
collective/registrationcaptcha/registrationform.py
collective/registrationcaptcha/profiles/default/browserlayer.xml
collective/registrationcaptcha/profiles/default/metadata.xml
collective/registrationcaptcha/profiles/uninstall/browserlayer.xml
docs/LICENSE-GPL.rst
docs/LICENSE-copyright.rst