Metadata-Version: 1.1
Name: collective.registrationcaptcha
Version: 1.1
Summary: Add a captcha field to the registration form.
Home-page: https://github.com/collective/collective.registrationcaptcha
Author: Johannes Raggam
Author-email: raggam-nl@adm.at
License: GPL
Keywords: plone user captcha
Platform: UNKNOWN
Classifier: Framework :: Plone
Classifier: Programming Language :: Python
